setup.cfg
setup.py
babelchart/__init__.py
babelchart/models.py
babelchart.egg-info/PKG-INFO
babelchart.egg-info/SOURCES.txt
babelchart.egg-info/dependency_links.txt
babelchart.egg-info/top_level.txt
babelchart/dependencies/__init__.py
babelchart/dependencies/gviz_api.py
babelchart/sinks/__init__.py
babelchart/sinks/googlecharts.py
babelchart/sinks/highcharts.py
babelchart/sources/__init__.py
babelchart/sources/cloudwatch.py
babelchart/sources/graphite.py
babelchart/sources/interface.py