Metadata-Version: 1.1
Name: babelchart
Version: 0.1.1
Summary: Pluggable timeseries data converter
Home-page: https://github.com/mbabineau/babelchart
Author: Mike Babineau
Author-email: michael.babineau@gmail.com
License: Apache v2.0
Platform: Posix; MacOS X; Windows
Classifier: Development Status :: 3 - Alpha
Classifier: Intended Audience :: Developers
Classifier: Intended Audience :: System Administrators
Classifier: License :: OSI Approved :: Apache Software License
Classifier: Operating System :: OS Independent
Classifier: Topic :: System :: Logging
